nlb_tools/__init__.py
nlb_tools/chop.py
nlb_tools/evaluation.py
nlb_tools/make_tensors.py
nlb_tools/nwb_interface.py
tests/__init__.py
tests/conftest.py
tests/test_evaluate.py
tests/test_make_tensors.py
tests/test_nlb.py
tests/test_nwb_interface.py
nlb_tools-0.0.4.dist-info/LICENSE
nlb_tools-0.0.4.dist-info/METADATA
nlb_tools-0.0.4.dist-info/WHEEL
nlb_tools-0.0.4.dist-info/top_level.txt
nlb_tools-0.0.4.dist-info/RECORD
