Metadata-Version: 2.1
Name: nlb-tools
Version: 0.0.4
Summary: Python tools for participating in Neural Latents Benchmark '21
Home-page: https://github.com/neurallatents/nlb_tools
Author: Felix Pei
License: MIT
Classifier: Intended Audience :: Science/Research
Classifier: Operating System :: Microsoft :: Windows
Classifier: Operating System :: MacOS
Classifier: Operating System :: Unix
Classifier: License :: OSI Approved :: MIT License
Classifier: Programming Language :: Python :: 3.7
Classifier: Programming Language :: Python :: 3.8
Classifier: Programming Language :: Python :: 3.9
Requires-Python: >=3.7
License-File: LICENSE
Requires-Dist: pandas (<=1.3.4,>=1.0.0)
Requires-Dist: scipy (>=1.1.0)
Requires-Dist: numpy
Requires-Dist: scikit-learn
Requires-Dist: h5py (<4,>=2.9)
Requires-Dist: pynwb
Provides-Extra: dev
Requires-Dist: pytest ; extra == 'dev'
Requires-Dist: dandi ; extra == 'dev'
